{
    "box": [
        "W   r",
        "     ",
        "     ",
        "     ",
        "     ",
        "     ",
        "W    ",
        "W    ",
        "     ",
        "B    ",
        "     ",
        "P    ",
        "     ",
        "W    ",
        "W    ",
        "W  r ",
        "     ",
        "W    ",
        "W    ",
        "W    ",
        "W    ",
        "W    ",
        "     ",
        "     ",
        "     ",
        "     ",
        "     ",
        "W    "
    ],
    "comment": "",
    "floor": [
        "     ",
        "     ",
        "     ",
        "     ",
        "F    ",
        "     ",
        "     ",
        "     ",
        "     ",
        "     ",
        "     ",
        "     ",
        "     ",
        "     ",
        "     ",
        "     ",
        "     ",
        "     ",
        "     ",
        "     ",
        "     ",
        "     ",
        "     ",
        "     ",
        "     ",
        "T    ",
        "     ",
        "     "
    ],
    "height": 4,
    "width": 7
}